{
  "date": "2026-03-13",
  "results": {
    "fx": true,
    "orlen_pl": true,
    "orlen_lt": true,
    "elvis_de": true,
    "bsh_se": true,
    "eu_bulletin": true
  },
  "data": {
    "fx": {
      "PLN_EUR": 4.2578,
      "SEK_EUR": 10.7108
    },
    "orlen_pl": {
      "price_pln_m3": 6399.0
    },
    "orlen_lt": {
      "price_eur_l": 1.1651
    },
    "elvis_de": {
      "price_eur_l": 2.163
    },
    "bsh_se": {
      "price_sek_l": 21.04
    },
    "eu_bulletin": {
      "LT": 1.901,
      "LV": 1.793,
      "EE": 1.688,
      "DK": 2.115,
      "SE": 1.783,
      "FI": 2.042,
      "EU_AVG": 1.748
    }
  }
}